jetbase/config.py
jetbase/constants.py
jetbase/enums.py
jetbase/exceptions.py
jetbase/models.py
jetbase/cli/main.py
jetbase/commands/current.py
jetbase/commands/fix_checksums.py
jetbase/commands/fix_files.py
jetbase/commands/history.py
jetbase/commands/init.py
jetbase/commands/lock_status.py
jetbase/commands/new.py
jetbase/commands/rollback.py
jetbase/commands/status.py
jetbase/commands/unlock.py
jetbase/commands/upgrade.py
jetbase/commands/validators.py
jetbase/database/connection.py
jetbase/database/queries/base.py
jetbase/database/queries/databricks.py
jetbase/database/queries/default_queries.py
jetbase/database/queries/mysql.py
jetbase/database/queries/postgres.py
jetbase/database/queries/query_loader.py
jetbase/database/queries/snowflake.py
jetbase/database/queries/sqlite.py
jetbase/engine/checksum.py
jetbase/engine/dry_run.py
jetbase/engine/file_parser.py
jetbase/engine/formatters.py
jetbase/engine/lock.py
jetbase/engine/repeatable.py
jetbase/engine/validation.py
jetbase/engine/version.py
jetbase/repositories/lock_repo.py
jetbase/repositories/migrations_repo.py
jetbase-0.17.2.dist-info/METADATA
jetbase-0.17.2.dist-info/WHEEL
jetbase-0.17.2.dist-info/entry_points.txt
jetbase-0.17.2.dist-info/licenses/LICENSE
jetbase-0.17.2.dist-info/RECORD
