Metadata-Version: 2.4
Name: jetbase
Version: 0.17.2
Summary: Jetbase is a Python database migration tool
Author-email: jaz <jaz.allibhai@gmail.com>
License-File: LICENSE
Requires-Python: >=3.10
Requires-Dist: packaging>=25.0
Requires-Dist: rich>=12.2.0
Requires-Dist: sqlalchemy>=2.0.10
Requires-Dist: tomli>=2.0.2
Requires-Dist: typer>=0.12.3
Provides-Extra: databricks
Requires-Dist: databricks-sqlalchemy>=2.0.1; extra == 'databricks'
Provides-Extra: snowflake
Requires-Dist: cryptography>=46.0.3; extra == 'snowflake'
Requires-Dist: snowflake-sqlalchemy>=1.8.2; extra == 'snowflake'
